{
  "last_update": "2026-07-24 08:15 KST",
  "buckets": [
    "3Y",
    "5Y",
    "7Y",
    "10Y",
    "20Y",
    "30Y"
  ],
  "matrix": {
    "AAPL": {
      "3Y": 12.9,
      "5Y": 20.1,
      "7Y": 12.1,
      "10Y": 22.6,
      "20Y": 68.2,
      "30Y": 55.7
    },
    "NVDA": {
      "3Y": 32.2,
      "5Y": 42.1,
      "7Y": 59.4,
      "10Y": 73.0,
      "20Y": 87.1,
      "30Y": 98.5
    },
    "META": {
      "3Y": 26.1,
      "5Y": 61.4,
      "7Y": 82.5,
      "10Y": 114.4,
      "20Y": 145.3,
      "30Y": 165.1
    },
    "GOOGL": {
      "3Y": 22.9,
      "5Y": 42.3,
      "7Y": 56.3,
      "10Y": 74.4,
      "20Y": 89.4,
      "30Y": 102.4
    },
    "MU": {
      "7Y": 73.4,
      "10Y": 68.0
    },
    "AVGO": {
      "3Y": 42.1,
      "5Y": 64.9,
      "7Y": 74.9,
      "10Y": 93.3,
      "30Y": 115.2
    },
    "AMZN": {
      "3Y": 39.4,
      "5Y": 52.7,
      "7Y": 61.9,
      "10Y": 81.3,
      "20Y": 99.8,
      "30Y": 118.4
    },
    "ORCL": {
      "3Y": 121.5,
      "5Y": 167.6,
      "7Y": 204.8,
      "10Y": 227.9,
      "20Y": 263.4,
      "30Y": 277.6
    }
  },
  "ratings": {
    "AAPL": "AA+ / Aaa",
    "NVDA": "AA / Aa1",
    "META": "AA- / Aa3",
    "GOOGL": "AA+ / Aa2",
    "MU": "BBB / Baa2",
    "AVGO": "A- / A3",
    "AMZN": "AA / A1",
    "ORCL": "BBB- / Baa2"
  },
  "bond_changes": [
    {
      "isin": "BY195434 Corp",
      "issuer": "AAPL",
      "name": "AAPL 3 1/4 08/08/29",
      "bucket": "3Y",
      "spread": 12.9,
      "d1": 0.5,
      "w1": -0.4,
      "mtd": 0.9,
      "ytd": -10.3
    },
    {
      "isin": "BQ791814 Corp",
      "issuer": "AAPL",
      "name": "AAPL 1.7 08/05/31",
      "bucket": "5Y",
      "spread": 20.1,
      "d1": 0.6,
      "w1": -0.2,
      "mtd": 0.2,
      "ytd": -5.5
    },
    {
      "isin": "ZK536545 Corp",
      "issuer": "AAPL",
      "name": "AAPL 4.3 05/10/33",
      "bucket": "7Y",
      "spread": 12.1,
      "d1": 0.4,
      "w1": -0.8,
      "mtd": -0.6,
      "ytd": 0.1
    },
    {
      "isin": "YO223460 Corp",
      "issuer": "AAPL",
      "name": "AAPL 4 3/4 05/12/35",
      "bucket": "10Y",
      "spread": 22.6,
      "d1": 0.4,
      "w1": 1.7,
      "mtd": -2.2,
      "ytd": -1.3
    },
    {
      "isin": "QZ067739 Corp",
      "issuer": "AAPL",
      "name": "AAPL 3.85 08/04/46",
      "bucket": "20Y",
      "spread": 68.2,
      "d1": 1.6,
      "w1": 3.3,
      "mtd": 3.3,
      "ytd": 11.6
    },
    {
      "isin": "ZK536546 Corp",
      "issuer": "AAPL",
      "name": "AAPL 4.85 05/10/53",
      "bucket": "30Y",
      "spread": 55.7,
      "d1": 3.7,
      "w1": 5.2,
      "mtd": 5.1,
      "ytd": 18.5
    },
    {
      "isin": "DL926553 Corp",
      "issuer": "NVDA",
      "name": "NVDA 4.35 06/15/29",
      "bucket": "3Y",
      "spread": 32.2,
      "d1": 0.4,
      "w1": -0.8,
      "mtd": 4.0,
      "ytd": null
    },
    {
      "isin": "DL926556 Corp",
      "issuer": "NVDA",
      "name": "NVDA 4 1/2 06/15/31",
      "bucket": "5Y",
      "spread": 42.1,
      "d1": 1.5,
      "w1": -0.7,
      "mtd": 6.4,
      "ytd": null
    },
    {
      "isin": "DL926560 Corp",
      "issuer": "NVDA",
      "name": "NVDA 4 3/4 06/15/33",
      "bucket": "7Y",
      "spread": 59.4,
      "d1": 3.5,
      "w1": 2.1,
      "mtd": 12.2,
      "ytd": null
    },
    {
      "isin": "DL926563 Corp",
      "issuer": "NVDA",
      "name": "NVDA 4.95 06/15/36",
      "bucket": "10Y",
      "spread": 73.0,
      "d1": 4.6,
      "w1": 6.6,
      "mtd": 12.5,
      "ytd": null
    },
    {
      "isin": "DL926565 Corp",
      "issuer": "NVDA",
      "name": "NVDA 5.55 06/15/46",
      "bucket": "20Y",
      "spread": 87.1,
      "d1": 4.8,
      "w1": 4.5,
      "mtd": 20.8,
      "ytd": null
    },
    {
      "isin": "DL926546 Corp",
      "issuer": "NVDA",
      "name": "NVDA 5 5/8 06/15/56",
      "bucket": "30Y",
      "spread": 98.5,
      "d1": 6.5,
      "w1": 9.7,
      "mtd": 25.3,
      "ytd": null
    },
    {
      "isin": "YW974691 Corp",
      "issuer": "META",
      "name": "META 4.3 08/15/29",
      "bucket": "3Y",
      "spread": 26.1,
      "d1": 1.8,
      "w1": 0.1,
      "mtd": 5.7,
      "ytd": -13.1
    },
    {
      "isin": "DK002336 Corp",
      "issuer": "META",
      "name": "META 4.55 05/15/31",
      "bucket": "5Y",
      "spread": 61.4,
      "d1": 2.4,
      "w1": 1.5,
      "mtd": 14.0,
      "ytd": null
    },
    {
      "isin": "DK002341 Corp",
      "issuer": "META",
      "name": "META 4 7/8 05/15/33",
      "bucket": "7Y",
      "spread": 82.5,
      "d1": 4.2,
      "w1": 4.6,
      "mtd": 10.9,
      "ytd": null
    },
    {
      "isin": "DK002349 Corp",
      "issuer": "META",
      "name": "META 5 1/4 05/15/36",
      "bucket": "10Y",
      "spread": 114.4,
      "d1": 10.6,
      "w1": 14.2,
      "mtd": 25.0,
      "ytd": null
    },
    {
      "isin": "DK002360 Corp",
      "issuer": "META",
      "name": "META 6.2 05/15/46",
      "bucket": "20Y",
      "spread": 145.3,
      "d1": 6.9,
      "w1": 8.0,
      "mtd": 19.8,
      "ytd": null
    },
    {
      "isin": "DK002368 Corp",
      "issuer": "META",
      "name": "META 6.3 05/15/56",
      "bucket": "30Y",
      "spread": 165.1,
      "d1": 7.3,
      "w1": 10.9,
      "mtd": 23.9,
      "ytd": null
    },
    {
      "isin": "YI913235 Corp",
      "issuer": "GOOGL",
      "name": "GOOGL 3.7 02/15/29",
      "bucket": "3Y",
      "spread": 22.9,
      "d1": 0.5,
      "w1": 0.2,
      "mtd": 3.9,
      "ytd": null
    },
    {
      "isin": "YI913236 Corp",
      "issuer": "GOOGL",
      "name": "GOOGL 4.1 02/15/31",
      "bucket": "5Y",
      "spread": 42.3,
      "d1": 5.4,
      "w1": 4.9,
      "mtd": 10.8,
      "ytd": null
    },
    {
      "isin": "YI913237 Corp",
      "issuer": "GOOGL",
      "name": "GOOGL 4.4 02/15/33",
      "bucket": "7Y",
      "spread": 56.3,
      "d1": 3.3,
      "w1": 4.8,
      "mtd": 10.2,
      "ytd": null
    },
    {
      "isin": "YI913238 Corp",
      "issuer": "GOOGL",
      "name": "GOOGL 4.8 02/15/36",
      "bucket": "10Y",
      "spread": 74.4,
      "d1": 5.8,
      "w1": 7.6,
      "mtd": 16.4,
      "ytd": null
    },
    {
      "isin": "YI913239 Corp",
      "issuer": "GOOGL",
      "name": "GOOGL 5 1/2 02/15/46",
      "bucket": "20Y",
      "spread": 89.4,
      "d1": 6.1,
      "w1": 7.9,
      "mtd": 20.2,
      "ytd": null
    },
    {
      "isin": "YI913240 Corp",
      "issuer": "GOOGL",
      "name": "GOOGL 5.65 02/15/56",
      "bucket": "30Y",
      "spread": 102.4,
      "d1": -0.7,
      "w1": 7.2,
      "mtd": 21.6,
      "ytd": null
    },
    {
      "isin": "ZK087872 Corp",
      "issuer": "MU",
      "name": "MU 5 7/8 09/15/33",
      "bucket": "7Y",
      "spread": 73.4,
      "d1": -1.9,
      "w1": -2.2,
      "mtd": -6.1,
      "ytd": -20.3
    },
    {
      "isin": "YP951000 Corp",
      "issuer": "MU",
      "name": "MU 6.05 11/01/35",
      "bucket": "10Y",
      "spread": 68.0,
      "d1": -1.4,
      "w1": -5.9,
      "mtd": -6.0,
      "ytd": -30.2
    },
    {
      "isin": "BS016828 Corp",
      "issuer": "MU",
      "name": "MU 3.366 11/01/41",
      "bucket": "EXTRA_15Y",
      "spread": 62.5,
      "d1": 2.8,
      "w1": 7.7,
      "mtd": 6.9,
      "ytd": -19.7
    },
    {
      "isin": "BV669408 Corp",
      "issuer": "AVGO",
      "name": "AVGO 4 04/15/29",
      "bucket": "3Y",
      "spread": 42.1,
      "d1": 0.5,
      "w1": -3.6,
      "mtd": 1.3,
      "ytd": -16.2
    },
    {
      "isin": "YK309642 Corp",
      "issuer": "AVGO",
      "name": "AVGO 2.45 02/15/31",
      "bucket": "5Y",
      "spread": 64.9,
      "d1": 4.7,
      "w1": 5.4,
      "mtd": 10.3,
      "ytd": 7.2
    },
    {
      "isin": "DC776281 Corp",
      "issuer": "AVGO",
      "name": "AVGO 4.6 01/15/33",
      "bucket": "7Y",
      "spread": 74.9,
      "d1": 5.0,
      "w1": 7.4,
      "mtd": 13.2,
      "ytd": null
    },
    {
      "isin": "DC776283 Corp",
      "issuer": "AVGO",
      "name": "AVGO 4.95 01/15/36",
      "bucket": "10Y",
      "spread": 93.3,
      "d1": 6.3,
      "w1": 10.7,
      "mtd": 19.3,
      "ytd": null
    },
    {
      "isin": "YK301350 Corp",
      "issuer": "AVGO",
      "name": "AVGO 3 1/2 02/15/41",
      "bucket": "EXTRA_15Y",
      "spread": 77.6,
      "d1": 9.0,
      "w1": 12.1,
      "mtd": 19.8,
      "ytd": 28.6
    },
    {
      "isin": "DC776285 Corp",
      "issuer": "AVGO",
      "name": "AVGO 5.7 01/15/56",
      "bucket": "30Y",
      "spread": 115.2,
      "d1": 8.4,
      "w1": 13.9,
      "mtd": 32.0,
      "ytd": null
    },
    {
      "isin": "DM926953 Corp",
      "issuer": "AMZN",
      "name": "AMZN 4.6 07/09/29",
      "bucket": "3Y",
      "spread": 39.4,
      "d1": 1.4,
      "w1": -0.2,
      "mtd": null,
      "ytd": null
    },
    {
      "isin": "DG517946 Corp",
      "issuer": "AMZN",
      "name": "AMZN 4 1/4 03/13/31",
      "bucket": "5Y",
      "spread": 52.7,
      "d1": 3.0,
      "w1": 4.9,
      "mtd": 12.0,
      "ytd": null
    },
    {
      "isin": "DG517949 Corp",
      "issuer": "AMZN",
      "name": "AMZN 4.55 03/13/33",
      "bucket": "7Y",
      "spread": 61.9,
      "d1": 1.9,
      "w1": 2.7,
      "mtd": 10.2,
      "ytd": null
    },
    {
      "isin": "DG517950 Corp",
      "issuer": "AMZN",
      "name": "AMZN 4 7/8 03/13/36",
      "bucket": "10Y",
      "spread": 81.3,
      "d1": 5.4,
      "w1": 7.1,
      "mtd": 17.2,
      "ytd": null
    },
    {
      "isin": "DG517952 Corp",
      "issuer": "AMZN",
      "name": "AMZN 5.65 03/13/46",
      "bucket": "20Y",
      "spread": 99.8,
      "d1": 4.3,
      "w1": 5.4,
      "mtd": 20.0,
      "ytd": null
    },
    {
      "isin": "DG517954 Corp",
      "issuer": "AMZN",
      "name": "AMZN 5.8 03/13/56",
      "bucket": "30Y",
      "spread": 118.4,
      "d1": 6.0,
      "w1": 10.0,
      "mtd": 25.5,
      "ytd": null
    },
    {
      "isin": "YI663392 Corp",
      "issuer": "ORCL",
      "name": "ORCL 4.55 02/04/29",
      "bucket": "3Y",
      "spread": 121.5,
      "d1": 3.3,
      "w1": 15.4,
      "mtd": 25.0,
      "ytd": null
    },
    {
      "isin": "YI663394 Corp",
      "issuer": "ORCL",
      "name": "ORCL 4.95 02/04/31",
      "bucket": "5Y",
      "spread": 167.6,
      "d1": 5.3,
      "w1": 23.2,
      "mtd": 41.8,
      "ytd": null
    },
    {
      "isin": "YI663395 Corp",
      "issuer": "ORCL",
      "name": "ORCL 5.35 05/04/33",
      "bucket": "7Y",
      "spread": 204.8,
      "d1": 11.5,
      "w1": 33.3,
      "mtd": 51.0,
      "ytd": null
    },
    {
      "isin": "YI663396 Corp",
      "issuer": "ORCL",
      "name": "ORCL 5.7 02/04/36",
      "bucket": "10Y",
      "spread": 227.9,
      "d1": 10.7,
      "w1": 32.2,
      "mtd": 60.7,
      "ytd": null
    },
    {
      "isin": "YI663397 Corp",
      "issuer": "ORCL",
      "name": "ORCL 6.55 02/04/46",
      "bucket": "20Y",
      "spread": 263.4,
      "d1": 3.0,
      "w1": 24.1,
      "mtd": 47.4,
      "ytd": null
    },
    {
      "isin": "YI663398 Corp",
      "issuer": "ORCL",
      "name": "ORCL 6.7 02/04/56",
      "bucket": "30Y",
      "spread": 277.6,
      "d1": 4.6,
      "w1": 25.2,
      "mtd": 52.1,
      "ytd": null
    }
  ],
  "bucket_chart": {
    "mtd": [
      6.8,
      13.6,
      12.6,
      17.9,
      21.9,
      26.5
    ],
    "ytd": [
      -13.2,
      0.9,
      -10.1,
      -15.8,
      11.6,
      18.5
    ]
  },
  "bucket_chart_by_issuer": {
    "AAPL": {
      "mtd": [
        0.9,
        0.2,
        -0.6,
        -2.2,
        3.3,
        5.1
      ],
      "ytd": [
        -10.3,
        -5.5,
        0.1,
        -1.3,
        11.6,
        18.5
      ]
    },
    "AMZN": {
      "mtd": [
        null,
        12.0,
        10.2,
        17.2,
        20.0,
        25.5
      ],
      "ytd": [
        null,
        null,
        null,
        null,
        null,
        null
      ]
    },
    "AVGO": {
      "mtd": [
        1.3,
        10.3,
        13.2,
        19.3,
        null,
        32.0
      ],
      "ytd": [
        -16.2,
        7.2,
        null,
        null,
        null,
        null
      ]
    },
    "GOOGL": {
      "mtd": [
        3.9,
        10.8,
        10.2,
        16.4,
        20.2,
        21.6
      ],
      "ytd": [
        null,
        null,
        null,
        null,
        null,
        null
      ]
    },
    "META": {
      "mtd": [
        5.7,
        14.0,
        10.9,
        25.0,
        19.8,
        23.9
      ],
      "ytd": [
        -13.1,
        null,
        null,
        null,
        null,
        null
      ]
    },
    "MU": {
      "mtd": [
        null,
        null,
        -6.1,
        -6.0,
        null,
        null
      ],
      "ytd": [
        null,
        null,
        -20.3,
        -30.2,
        null,
        null
      ]
    },
    "NVDA": {
      "mtd": [
        4.0,
        6.4,
        12.2,
        12.5,
        20.8,
        25.3
      ],
      "ytd": [
        null,
        null,
        null,
        null,
        null,
        null
      ]
    },
    "ORCL": {
      "mtd": [
        25.0,
        41.8,
        51.0,
        60.7,
        47.4,
        52.1
      ],
      "ytd": [
        null,
        null,
        null,
        null,
        null,
        null
      ]
    }
  }
}